{
  "dn32:1.0": "Ich glaube, das ist die einzige Stelle im ganzen Kanon, die das bhanavara am Anfang bringt. (Sujato) ",
  "dn32:2.14": "Siehe Sujatos Essay: https://discourse.suttacentral.net/t/a-note-on-pavacana/4480 ",
  "dn32:3.2": "Siehe Sujatos Anmerkung. ",
  "dn32:4.29": "Siehe Sujatos Anmerkung. ",
  "dn32:7.12": "Siehe Sujatos Anmerkung. ",
  "dn32:7.13": "Siehe Sujatos Anmerkung zu den Hufen. ",
  "dn32:7.17": "Ich denke und hoffe, hier ist eine Rickscha gemeint und nicht Huckepack. (Sujato) ",
  "dn32:7.59": "_Kuḷīrakā_ scheint der Name eines Krabben (_kuḷīra_) fressenden Vogels zu sein. Zu Ehren meines Geburtslandes nenne ich ihn nach dem Kookaburra, der Krabben frisst und für seinen Schrei berühmt ist. (Sujato) "
}