{
  "ja396:5.3": "siṃsapā → sasiṃsapā (bj, pts-vp-pli1ed) | sā sīsapā (sya1ed, sya2ed) | yā siṃsapā (si -nissya)",
  "ja396:5.4": "upparito → uparito (bj, sya1ed, sya2ed, pts-vp-pli1ed)",
  "ja396:6.2": "Parikiriya → pakiriyā (mr), samaṃ ṭhitā → samaṭṭhitā (bj, sya1ed, sya2ed)",
  "ja396:6.3": "Tāhi susaṅgahitā balasā pīḷitā → tā saṅgahitā balasā ca pīḷitā (bj) | tāhi susaṅgahitā balasā ca pīḷitā (sya1ed, sya2ed) | tāhi saṅgahītā balasā papīḷitā (pts-vp-pli1ed)",
  "ja396:8.4": "tanubandhamuddharaṃ → tanuvaṭṭamuddharaṃ (bj, pts-vp-pli1ed)"
}