{
  "ja437:6.3": "Pajjhāyi → pajjhāti (bj, pts1) | pajjhāyati (bj -nissya)",
  "ja437:6.4": "meṇḍamātaraṃ → meḷamātaraṃ (bj, pts1)",
  "ja437:7.3": "tvaṃ → so tvaṃ (s2, s3)",
  "ja437:8.3": "pajjhāyi → pajjhāti (bj, pts1) | pajjhāyati (bj -nissya)",
  "ja437:9.4": "piyapucchikā → pucchitā (s2, s3, mr)",
  "ja437:10.3": "parivārena → parihārena (s2)",
  "ja437:10.4": "essaṃ → esaṃ (si, pts1), kayirāhi → kayirāsi (pts1)",
  "ja437:11.4": "taṃ → te (si, s2, s3, pts1)",
  "ja437:12.4": "kayirāhi → kayirāsi (pts1)",
  "ja437:13.3": "vajjaṃ → vacchaṃ (?)"
}