{
  "thag3.6:1.1": "<article id='thag3.6'><header><ul><li class='division'>",
  "thag3.6:2.1": "</li><li>",
  "thag3.6:3.1": "</li><li>",
  "thag3.6:4.1": "</li></ul><h1>",
  "thag3.6:5.1": "</h1></header><blockquote class='gatha'><p><a class='sc' id='1'></a><a class='vns' id='vns234'></a><a class='vnp' id='vnp234'></a>",
  "thag3.6:5.2": "<br>",
  "thag3.6:5.3": "<br>",
  "thag3.6:5.4": "<br>",
  "thag3.6:6.1": "</p><p><a class='sc' id='2'></a><a class='vns' id='vns235'></a><a class='vnp' id='vnp235'></a>",
  "thag3.6:6.2": "<br>",
  "thag3.6:6.3": "<br>",
  "thag3.6:6.4": "<br>",
  "thag3.6:7.1": "</p><p><a class='sc' id='3'></a><a class='vns' id='vns236'></a><a class='vnp' id='vnp236'></a>",
  "thag3.6:7.2": "<br>",
  "thag3.6:7.3": "<br>",
  "thag3.6:7.4": "<br>",
  "thag3.6:8.1": "</p></blockquote><p class='endsutta'>",
  "thag3.6:8.2": "",
  "~": "</p></article>"
}