{
  "thag2.17:1.1": "<article id='thag2.17'><header><ul><li class='division'>",
  "thag2.17:2.1": "</li><li>",
  "thag2.17:3.1": "</li><li>",
  "thag2.17:4.1": "</li></ul><h1>",
  "thag2.17:5.1": "</h1></header><blockquote class='gatha'><p><a class='sc' id='1'></a><a class='vns' id='vns153'></a><a class='vnp' id='vnp153'></a>",
  "thag2.17:5.2": "<br>",
  "thag2.17:5.3": "<br>",
  "thag2.17:5.4": "<br>",
  "thag2.17:6.1": "</p><p><a class='sc' id='2'></a><a class='vns' id='vns154'></a><a class='vnp' id='vnp154'></a>",
  "thag2.17:6.2": "<br>",
  "thag2.17:6.3": "<br>",
  "thag2.17:6.4": "<br>",
  "thag2.17:7.1": "</p></blockquote><p class='endsutta'>",
  "thag2.17:7.2": "",
  "~": "</p></article>"
}