{
  "thig1.11:1.1": "<article id='thig1.11'><header><ul><li class='division'>{}</li>",
  "thig1.11:2.1": "<li>{}</li></ul>",
  "thig1.11:3.1": "<h1 class='sutta-title'>{}</h1></header>",
  "thig1.11:4.1": "<blockquote class='gatha'><p><a class='sc' id='1'></a><a class='vns' id='vns11'></a><a class='vnp' id='vnp11'></a>{}<br>",
  "thig1.11:4.2": "{}<br>",
  "thig1.11:4.3": "{}<br>",
  "thig1.11:4.4": "{}<br>",
  "thig1.11:4.5": "{}<br>",
  "thig1.11:4.6": "{}</p></blockquote>",
  "thig1.11:5.1": "<p class='endsutta'><a class='sc' id='2'></a>{}",
  "thig1.11:5.2": "{}</p></article>"
}