{
  "thig2.5:1.1": "<article id='thig2.5'><header><ul><li class='division'>{}</li>",
  "thig2.5:2.1": "<li>{}</li></ul>",
  "thig2.5:3.1": "<h1 class='sutta-title'>{}</h1></header>",
  "thig2.5:4.1": "<blockquote class='gatha'><p><a class='sc' id='1'></a><a class='vns' id='vns27'></a><a class='vnp' id='vnp27'></a>{}<br>",
  "thig2.5:4.2": "{}<br>",
  "thig2.5:4.3": "{}<br>",
  "thig2.5:4.4": "{}</p>",
  "thig2.5:5.1": "<p><a class='sc' id='2'></a><a class='vns' id='vns28'></a><a class='vnp' id='vnp28'></a>{}<br>",
  "thig2.5:5.2": "{}<br>",
  "thig2.5:5.3": "{}<br>",
  "thig2.5:5.4": "{}</p></blockquote>",
  "thig2.5:6.1": "<p class='endsutta'><a class='sc' id='3'></a>{}",
  "thig2.5:6.2": "{}</p></article>"
}