{
  "mil6.3.6:6.6": "laguḷahatāni → lakuṭahatāni (bj, pts1, mr) | sakuṇapahatā (maku)",
  "mil6.3.6:9.2": "sāmayikā → sāmāyikā (maku, pts1, mr)",
  "mil6.3.6:10.2": "ahidaṭṭhā → ahinā daṭṭho (bj, maku, pts1)",
  "mil6.3.6:11.2": "bubhukkhito visukkhito → bubhukkhito susukkhito (bj) | sukkhito visukkhito (si, pts1) | dukkhito visukkhito (maku)",
  "mil6.3.6:16.1": "khubbhitacitto → khubhitacitto (bj, pts1) | nāvāgato (maku), udakeneva → udake yeva (bj, maku, pts1)",
  "mil6.3.6:28.1": "otatavitataākiṇṇabahuphalaṃ hutvā → uṭṭhitaākiṇṇabahuphalaṃ bhavitvā (maku)",
  "mil6.3.6:33.1": "Akālamaraṇapañho → kālākālamaraṇapañho (maku)"
}