{
  "ja470:5.1": "sc1,  pts4.186",
  "ja470:6.1": "sc2",
  "ja470:7.1": "sc3",
  "ja470:8.1": "sc4",
  "ja470:9.1": "sc5",
  "ja470:10.1": "sc6",
  "ja470:11.1": "sc7",
  "ja470:12.1": "sc8",
  "ja470:13.1": "sc9",
  "ja470:14.1": "sc10",
  "ja470:15.1": "sc11",
  "ja470:16.1": "sc12",
  "ja470:17.1": "sc13",
  "ja470:18.1": "sc14",
  "ja470:19.1": "sc15",
  "ja470:20.1": "sc16",
  "ja470:21.1": "sc17",
  "ja470:22.1": "sc18",
  "ja470:23.1": "sc19",
  "ja470:24.1": "sc20",
  "ja470:25.1": "sc21",
  "ja470:26.1": "sc22"
}