{
  "pli-tv-kd11:0.5": "sc1, ms-pa41, pts-vp-en5.1, pts-vp-pli2.1, pts-cs-Kd.11.1.1",
  "pli-tv-kd11:1.1.1": "sc2, pts-vp-pli2.1 , ms-pa42",
  "pli-tv-kd11:1.2.1": "pts-cs-Kd.11.1.2",
  "pli-tv-kd11:1.2.9": "sc3, pts-vp-pli2.2 , ms-pa43, pts-vp-en5.2",
  "pli-tv-kd11:1.2.11": "pts-vp-pli2.2",
  "pli-tv-kd11:1.3.1": "sc4, ms-pa44, pts-cs-Kd.11.1.3",
  "pli-tv-kd11:1.4.1": "pts-cs-Kd.11.1.4",
  "pli-tv-kd11:1.4.2": "pts-vp-en5.3",
  "pli-tv-kd11:1.4.3": "sc5 , ms-pa45",
  "pli-tv-kd11:1.4.13": "sc6 , ms-pa46",
  "pli-tv-kd11:1.4.26": "sc7 , ms-pa47",
  "pli-tv-kd11:1.4.40": "sc8 , ms-pa48",
  "pli-tv-kd11:1.4.54": "sc9 , ms-pa49",
  "pli-tv-kd11:2.1.1": "sc10, pts-vp-pli2.3, pts-cs-Kd.11.2.1, pts-vp-pli2.3, ms-pa410",
  "pli-tv-kd11:2.1.2": "pts-vp-en5.4",
  "pli-tv-kd11:2.1.4": "sc11 , ms-pa411",
  "pli-tv-kd11:2.1.7": "sc12 , ms-pa412",
  "pli-tv-kd11:2.1.10": "sc13 , ms-pa413",
  "pli-tv-kd11:2.1.13": "sc14 , ms-pa414",
  "pli-tv-kd11:2.1.16": "sc15 , ms-pa415",
  "pli-tv-kd11:2.1.19": "sc16 , ms-pa416",
  "pli-tv-kd11:2.1.22": "sc17 , ms-pa417",
  "pli-tv-kd11:2.1.23": "pts-vp-en5.5",
  "pli-tv-kd11:2.1.25": "sc18 , ms-pa418",
  "pli-tv-kd11:2.1.28": "sc19 , ms-pa419",
  "pli-tv-kd11:2.1.31": "sc20 , ms-pa420",
  "pli-tv-kd11:2.1.34": "sc21 , ms-pa421",
  "pli-tv-kd11:2.2.1": "sc22 , ms-pa422",
  "pli-tv-kd11:3.1.1": "sc23 , pts-cs-Kd.11.3.1, ms-pa423",
  "pli-tv-kd11:3.1.4": "sc24, pts-vp-pli2.4 , ms-pa424",
  "pli-tv-kd11:3.1.5": "pts-vp-pli2.4",
  "pli-tv-kd11:3.1.7": "sc25 , ms-pa425",
  "pli-tv-kd11:3.1.10": "sc26 , ms-pa426",
  "pli-tv-kd11:3.1.13": "sc27 , ms-pa427",
  "pli-tv-kd11:3.1.16": "sc28 , ms-pa428",
  "pli-tv-kd11:3.1.19": "sc29 , ms-pa429",
  "pli-tv-kd11:3.1.22": "sc30 , ms-pa430",
  "pli-tv-kd11:3.1.25": "sc31 , ms-pa431",
  "pli-tv-kd11:3.1.26": "pts-vp-en5.6",
  "pli-tv-kd11:3.1.28": "sc32 , ms-pa432",
  "pli-tv-kd11:3.1.31": "sc33 , ms-pa433",
  "pli-tv-kd11:3.1.34": "sc34 , ms-pa434",
  "pli-tv-kd11:3.2.1": "sc35 , ms-pa435",
  "pli-tv-kd11:4.1.1": "sc36 , pts-cs-Kd.11.4.1, ms-pa436",
  "pli-tv-kd11:4.1.6": "sc37 , ms-pa437",
  "pli-tv-kd11:4.1.9": "sc38 , ms-pa438",
  "pli-tv-kd11:4.2.1": "sc39 , pts-cs-Kd.11.4.2, ms-pa4.39, pts-vp-en5.7",
  "pli-tv-kd11:4.2.6": "sc40 , ms-pa440",
  "pli-tv-kd11:4.2.9": "sc41, pts-vp-pli2.5 , ms-pa441",
  "pli-tv-kd11:4.2.10": "pts-vp-pli2.5",
  "pli-tv-kd11:4.3.1": "sc42 , ms-pa442",
  "pli-tv-kd11:5.1.1": "sc43 , pts-cs-Kd.11.5.1, ms-pa443",
  "pli-tv-kd11:5.2.1": "sc44 , ms-pa444",
  "pli-tv-kd11:6.1.1": "sc45 , pts-cs-Kd.11.6.1, ms-pa445",
  "pli-tv-kd11:6.2.1": "sc46 , pts-cs-Kd.11.6.2, ms-pa446",
  "pli-tv-kd11:6.2.4": "sc47 , ms-pa447",
  "pli-tv-kd11:6.2.5": "pts-vp-en5.9",
  "pli-tv-kd11:6.2.8": "sc48, pts-vp-pli2.6 , ms-pa4.48, pts-vp-pli2.6",
  "pli-tv-kd11:6.3.1": "sc49 , ms-pa449",
  "pli-tv-kd11:7.1.1": "sc50 , pts-cs-Kd.11.7.1, ms-pa450",
  "pli-tv-kd11:7.1.4": "sc51 , ms-pa451",
  "pli-tv-kd11:7.1.8": "sc52 , ms-pa452",
  "pli-tv-kd11:8.1.1": "sc53 , ms-pa453",
  "pli-tv-kd11:8.1.2": "sc54 , pts-cs-Kd.11.8.1, ms-pa454",
  "pli-tv-kd11:8.1.3": "pts-vp-en5.10",
  "pli-tv-kd11:8.2.1": "sc55, pts-vp-pli2.7 , pts-cs-Kd.11.8.2, ms-pa455",
  "pli-tv-kd11:8.2.2": "pts-vp-pli2.7",
  "pli-tv-kd11:8.2.5": "sc56 , ms-pa456",
  "pli-tv-kd11:8.2.10": "sc57 , ms-pa457",
  "pli-tv-kd11:8.2.16": "sc58 , ms-pa458",
  "pli-tv-kd11:8.2.22": "sc59 , ms-pa459",
  "pli-tv-kd11:8.2.24": "sc60 , ms-pa460",
  "pli-tv-kd11:9.1.1": "sc61 , pts-cs-Kd.11.9.1, ms-pa4.61, pts-vp-en5.11",
  "pli-tv-kd11:9.1.9": "sc62, pts-vp-pli2.8 , ms-pa462",
  "pli-tv-kd11:9.1.22": "pts-vp-pli2.8",
  "pli-tv-kd11:9.2.1": "pts-cs-Kd.11.9.2",
  "pli-tv-kd11:9.2.3": "sc63 , ms-pa463",
  "pli-tv-kd11:9.2.6": "pts-vp-en5.12",
  "pli-tv-kd11:9.2.10": "sc64 , ms-pa464",
  "pli-tv-kd11:9.2.19": "sc65 , ms-pa465",
  "pli-tv-kd11:9.2.30": "sc66 , ms-pa466",
  "pli-tv-kd11:10.1.1": "sc67 , pts-cs-Kd.11.10.1, ms-pa467",
  "pli-tv-kd11:10.1.4": "sc68 , ms-pa468",
  "pli-tv-kd11:10.1.7": "sc69 , ms-pa469",
  "pli-tv-kd11:10.1.10": "sc70 , ms-pa470",
  "pli-tv-kd11:10.1.13": "sc71 , ms-pa471",
  "pli-tv-kd11:10.1.16": "sc72 , ms-pa472",
  "pli-tv-kd11:10.1.19": "sc73 , ms-pa473",
  "pli-tv-kd11:10.1.22": "sc74 , ms-pa474",
  "pli-tv-kd11:10.1.25": "sc75 , ms-pa475",
  "pli-tv-kd11:10.1.28": "sc76 , ms-pa476",
  "pli-tv-kd11:10.1.31": "sc77 , ms-pa477",
  "pli-tv-kd11:10.1.34": "sc78 , ms-pa478",
  "pli-tv-kd11:10.1.37": "sc79 , ms-pa479",
  "pli-tv-kd11:10.1.39": "sc80 , ms-pa480",
  "pli-tv-kd11:10.1.42": "sc81 , ms-pa481",
  "pli-tv-kd11:10.1.45": "sc82 , ms-pa482",
  "pli-tv-kd11:10.1.48": "sc83 , ms-pa483",
  "pli-tv-kd11:10.1.51": "sc84 , ms-pa484",
  "pli-tv-kd11:10.1.54": "sc85 , ms-pa485",
  "pli-tv-kd11:10.1.57": "sc86 , ms-pa486",
  "pli-tv-kd11:10.1.60": "sc87 , ms-pa487",
  "pli-tv-kd11:10.1.63": "sc88 , ms-pa488",
  "pli-tv-kd11:10.1.66": "sc89 , ms-pa489",
  "pli-tv-kd11:10.1.69": "sc90 , ms-pa490",
  "pli-tv-kd11:10.1.72": "sc91 , ms-pa491",
  "pli-tv-kd11:10.1.75": "sc92 , ms-pa492",
  "pli-tv-kd11:10.1.77": "sc93 , ms-pa493",
  "pli-tv-kd11:10.1.82": "sc94 , ms-pa494",
  "pli-tv-kd11:10.1.85": "sc95 , ms-pa495",
  "pli-tv-kd11:10.1.88": "sc96 , ms-pa496",
  "pli-tv-kd11:10.1.93": "sc97 , ms-pa497",
  "pli-tv-kd11:10.1.96": "sc98 , ms-pa498",
  "pli-tv-kd11:10.1.99": "sc99 , ms-pa499",
  "pli-tv-kd11:10.1.101": "sc100 , ms-pa4100",
  "pli-tv-kd11:10.2.1": "sc101 , ms-pa4101",
  "pli-tv-kd11:11.1.1": "sc102 , pts-cs-Kd.11.11.1, ms-pa4102",
  "pli-tv-kd11:11.1.6": "pts-vp-en5.13",
  "pli-tv-kd11:11.2.1": "sc103 , pts-cs-Kd.11.11.2, ms-pa4.103, pts-vp-pli2.9",
  "pli-tv-kd11:11.2.4": "sc104 , ms-pa4104",
  "pli-tv-kd11:11.2.8": "sc105 , ms-pa4105",
  "pli-tv-kd11:11.2.11": "sc106 , ms-pa4106",
  "pli-tv-kd11:11.2.13": "sc107 , ms-pa4107",
  "pli-tv-kd11:11.2.16": "sc108 , ms-pa4108",
  "pli-tv-kd11:11.2.20": "sc109, pts-vp-pli2.9 , ms-pa4109",
  "pli-tv-kd11:11.3.1": "sc110 , ms-pa4110",
  "pli-tv-kd11:12.1.1": "sc111 , pts-cs-Kd.11.12.1, ms-pa4111",
  "pli-tv-kd11:12.2.1": "pts-cs-Kd.11.12.2",
  "pli-tv-kd11:12.2.2": "sc112 , ms-pa4112",
  "pli-tv-kd11:12.2.6": "sc113 , ms-pa4113",
  "pli-tv-kd11:12.2.11": "sc114 , ms-pa4114",
  "pli-tv-kd11:12.2.17": "sc115 , ms-pa4115",
  "pli-tv-kd11:12.2.21": "pts-vp-en5.14",
  "pli-tv-kd11:12.2.23": "sc116 , ms-pa4116",
  "pli-tv-kd11:12.2.25": "sc117 , ms-pa4117",
  "pli-tv-kd11:13.1.1": "sc118, pts-vp-pli2.10, pts-cs-Kd.11.13.1, ms-pa4118",
  "pli-tv-kd11:13.1.3": "pts-vp-pli2.10",
  "pli-tv-kd11:13.1.6": "pts-vp-en5.15",
  "pli-tv-kd11:13.2.1": "pts-cs-Kd.11.13.2",
  "pli-tv-kd11:13.3.1": "sc119, pts-vp-pli2.11, pts-cs-Kd.11.13.3, ms-pa4119",
  "pli-tv-kd11:13.3.4": "pts-vp-pli2.11",
  "pli-tv-kd11:13.3.8": "sc120 , ms-pa4120",
  "pli-tv-kd11:13.3.9": "pts-vp-en5.16",
  "pli-tv-kd11:13.4.1": "pts-cs-Kd.11.13.4",
  "pli-tv-kd11:13.4.10": "sc121",
  "pli-tv-kd11:13.4.21": "ms-pa4121",
  "pli-tv-kd11:13.5.1": "sc122, pts-vp-pli2.12 , pts-cs-Kd.11.13.5, ms-pa4122",
  "pli-tv-kd11:13.5.10": "pts-vp-pli2.12, pts-vp-en5.17",
  "pli-tv-kd11:13.6.1": "sc123 , pts-cs-Kd.11.13.6, ms-pa4123",
  "pli-tv-kd11:13.6.32": "sc124, pts-vp-pli2.13 , pts-vp-en5.18, ms-pa4124",
  "pli-tv-kd11:13.7.1": "pts-cs-Kd.11.13.7",
  "pli-tv-kd11:13.7.2": "pts-vp-pli2.13",
  "pli-tv-kd11:13.7.3": "sc125 , ms-pa4125",
  "pli-tv-kd11:13.7.10": "sc126 , ms-pa4126",
  "pli-tv-kd11:13.7.18": "sc127 , ms-pa4127",
  "pli-tv-kd11:13.7.28": "sc128 , ms-pa4128",
  "pli-tv-kd11:14.1.1": "sc129 , pts-cs-Kd.11.14.1, ms-pa4.129, pts-vp-en5.19",
  "pli-tv-kd11:14.1.4": "sc130 , ms-pa4130",
  "pli-tv-kd11:14.1.17": "sc131 , ms-pa4131",
  "pli-tv-kd11:14.1.19": "sc132 , ms-pa4132",
  "pli-tv-kd11:14.1.22": "sc133 , ms-pa4133",
  "pli-tv-kd11:14.1.35": "sc134 , ms-pa4134",
  "pli-tv-kd11:14.1.37": "sc135 , ms-pa4135",
  "pli-tv-kd11:14.1.42": "sc136 , ms-pa4136",
  "pli-tv-kd11:14.1.45": "sc137 , ms-pa4137",
  "pli-tv-kd11:14.1.48": "sc138 , ms-pa4138",
  "pli-tv-kd11:14.1.51": "sc139 , ms-pa4139",
  "pli-tv-kd11:14.1.54": "sc140 , ms-pa4140",
  "pli-tv-kd11:14.1.57": "sc141 , ms-pa4141",
  "pli-tv-kd11:14.2.1": "sc142, pts-vp-pli2.14 , pts-cs-Kd.11.14.2, ms-pa4142",
  "pli-tv-kd11:14.2.2": "pts-vp-pli2.14",
  "pli-tv-kd11:14.2.6": "sc143 , ms-pa4143",
  "pli-tv-kd11:14.2.9": "sc144 , ms-pa4144",
  "pli-tv-kd11:14.2.10": "pts-vp-en5.20",
  "pli-tv-kd11:14.2.12": "sc145 , ms-pa4145",
  "pli-tv-kd11:14.2.15": "sc146 , ms-pa4146",
  "pli-tv-kd11:14.2.18": "sc147 , ms-pa4147",
  "pli-tv-kd11:14.2.21": "sc148 , ms-pa4148",
  "pli-tv-kd11:14.2.24": "sc149 , ms-pa4149",
  "pli-tv-kd11:15.1.1": "sc150 , pts-cs-Kd.11.15.1, ms-pa4150",
  "pli-tv-kd11:15.2.1": "sc151 , ms-pa4151",
  "pli-tv-kd11:16.1.1": "sc152 , pts-cs-Kd.11.16.1, ms-pa4152",
  "pli-tv-kd11:16.1.8": "pts-vp-en5.21",
  "pli-tv-kd11:16.1.13": "sc153 , ms-pa4153",
  "pli-tv-kd11:16.2.1": "sc154, pts-vp-pli2.15 , pts-cs-Kd.11.16.2, ms-pa4.154, pts-vp-pli2.15",
  "pli-tv-kd11:16.2.4": "sc155 , ms-pa4155",
  "pli-tv-kd11:16.2.8": "sc156 , ms-pa4156",
  "pli-tv-kd11:16.2.11": "sc157 , ms-pa4157",
  "pli-tv-kd11:16.3.1": "sc158 , ms-pa4158",
  "pli-tv-kd11:16.3.4": "sc159 , ms-pa4159",
  "pli-tv-kd11:16.3.8": "sc160 , ms-pa4160",
  "pli-tv-kd11:16.3.11": "sc161 , ms-pa4161",
  "pli-tv-kd11:17.1.1": "sc162 , pts-cs-Kd.11.17.1, ms-pa4162",
  "pli-tv-kd11:17.1.6": "pts-vp-en5.22",
  "pli-tv-kd11:17.2.1": "sc163 , pts-cs-Kd.11.17.2, ms-pa4163",
  "pli-tv-kd11:17.2.5": "sc164 , ms-pa4164",
  "pli-tv-kd11:17.2.10": "sc165 , ms-pa4165",
  "pli-tv-kd11:17.2.17": "sc166 , ms-pa4166",
  "pli-tv-kd11:17.2.19": "sc167 , ms-pa4167",
  "pli-tv-kd11:18.1.1": "sc168 , pts-cs-Kd.11.18.1, ms-pa4168",
  "pli-tv-kd11:18.1.3": "sc169, pts-vp-pli2.16 , ms-pa4169, pts-vp-pli2.16, pts-vp-en5.23",
  "pli-tv-kd11:18.1.4": "sc170 , ms-pa4170",
  "pli-tv-kd11:18.1.7": "sc171 , ms-pa4171",
  "pli-tv-kd11:18.2.1": "sc172 , pts-cs-Kd.11.18.2, ms-pa4172",
  "pli-tv-kd11:18.2.13": "pts-vp-en5.24",
  "pli-tv-kd11:18.3.1": "sc173, pts-vp-pli2.17 , pts-cs-Kd.11.18.3, ms-pa4173",
  "pli-tv-kd11:18.3.3": "pts-vp-pli2.17",
  "pli-tv-kd11:18.4.1": "pts-cs-Kd.11.18.4",
  "pli-tv-kd11:18.4.4": "pts-vp-en5.25",
  "pli-tv-kd11:18.5.1": "sc174, pts-vp-pli2.18 , pts-cs-Kd.11.18.5, ms-pa4174",
  "pli-tv-kd11:18.5.3": "pts-vp-pli2.18",
  "pli-tv-kd11:18.5.4": "sc175 , ms-pa4175",
  "pli-tv-kd11:18.6.1": "pts-cs-Kd.11.18.6",
  "pli-tv-kd11:18.6.2": "pts-vp-en5.26",
  "pli-tv-kd11:18.6.3": "sc176 , ms-pa4176",
  "pli-tv-kd11:18.6.8": "sc177 , ms-pa4177",
  "pli-tv-kd11:18.6.14": "sc178 , ms-pa4178",
  "pli-tv-kd11:18.6.22": "sc179 , ms-pa4179",
  "pli-tv-kd11:19.1.1": "sc180 , pts-cs-Kd.11.19.1, ms-pa4180",
  "pli-tv-kd11:19.1.4": "sc181 , ms-pa4181",
  "pli-tv-kd11:19.1.17": "sc182 , ms-pa4182",
  "pli-tv-kd11:19.1.19": "sc183 , ms-pa4183",
  "pli-tv-kd11:19.1.22": "sc184 , ms-pa4184",
  "pli-tv-kd11:19.1.35": "sc185 , ms-pa4185",
  "pli-tv-kd11:20.1.1": "sc186, pts-vp-pli2.19 , pts-cs-Kd.11.20.1, ms-pa4186",
  "pli-tv-kd11:20.1.2": "pts-vp-pli2.19",
  "pli-tv-kd11:20.1.4": "sc187 , pts-vp-en5.27, ms-pa4187",
  "pli-tv-kd11:20.1.7": "sc188 , ms-pa4188",
  "pli-tv-kd11:20.1.10": "sc189 , ms-pa4189",
  "pli-tv-kd11:20.2.1": "sc190 , ms-pa4190",
  "pli-tv-kd11:21.1.1": "sc191 , pts-cs-Kd.11.21.1, ms-pa4191",
  "pli-tv-kd11:21.2.1": "sc192 , ms-pa4192",
  "pli-tv-kd11:22.1.1": "sc193 , pts-vp-en5.28, pts-cs-Kd.11.22.1, ms-pa4193",
  "pli-tv-kd11:22.2.2": "pts-cs-Kd.11.22.2",
  "pli-tv-kd11:22.2.6": "sc194 , ms-pa4194",
  "pli-tv-kd11:22.2.9": "sc195, pts-vp-pli2.20 , ms-pa4195",
  "pli-tv-kd11:22.2.10": "pts-vp-pli2.20",
  "pli-tv-kd11:22.2.13": "sc196 , ms-pa4196",
  "pli-tv-kd11:22.3.1": "sc197 , pts-cs-Kd.11.22.3, ms-pa4197",
  "pli-tv-kd11:22.3.3": "pts-vp-en5.29",
  "pli-tv-kd11:23.1.1": "sc198 , pts-cs-Kd.11.23.1, ms-pa4198",
  "pli-tv-kd11:23.2.1": "sc199 , pts-cs-Kd.11.23.2, ms-pa4199",
  "pli-tv-kd11:23.2.4": "sc200 , ms-pa4200",
  "pli-tv-kd11:23.2.8": "sc201 , ms-pa4201",
  "pli-tv-kd11:23.2.11": "sc202 , ms-pa4202",
  "pli-tv-kd11:23.2.13": "sc203 , ms-pa4203",
  "pli-tv-kd11:23.2.16": "sc204 , ms-pa4204",
  "pli-tv-kd11:23.2.20": "sc205 , ms-pa4205",
  "pli-tv-kd11:23.3.1": "sc206 , ms-pa4206",
  "pli-tv-kd11:24.1.1": "sc207, pts-vp-pli2.21 , pts-vp-pli2.21, pts-vp-en5.30, pts-cs-Kd.11.24.1, ms-pa4207",
  "pli-tv-kd11:24.1.7": "sc208 , ms-pa4208",
  "pli-tv-kd11:24.1.11": "sc209 , ms-pa4209",
  "pli-tv-kd11:24.1.16": "sc210 , ms-pa4210",
  "pli-tv-kd11:24.1.23": "sc211 , ms-pa4211",
  "pli-tv-kd11:24.1.25": "sc212 , ms-pa4212",
  "pli-tv-kd11:24.1.27": "sc213 , pts-cs-Kd.11.25.1, ms-pa4213",
  "pli-tv-kd11:24.1.32": "sc214 , ms-pa4214",
  "pli-tv-kd11:25.1.1": "pts-cs-Kd.11.25.2",
  "pli-tv-kd11:25.1.3": "sc215 , ms-pa4215",
  "pli-tv-kd11:25.1.8": "sc216 , ms-pa4216",
  "pli-tv-kd11:25.1.9": "pts-vp-en5.31",
  "pli-tv-kd11:25.1.15": "sc217, pts-vp-pli2.22 , ms-pa4217",
  "pli-tv-kd11:25.1.23": "pts-vp-pli2.22",
  "pli-tv-kd11:25.1.24": "sc218 , ms-pa4218",
  "pli-tv-kd11:25.1.27": "sc219 , ms-pa4219",
  "pli-tv-kd11:26.1.1": "sc220 , pts-cs-Kd.11.26.1, ms-pa4220",
  "pli-tv-kd11:26.1.4": "sc221 , ms-pa4221",
  "pli-tv-kd11:26.1.17": "sc222 , ms-pa4222",
  "pli-tv-kd11:26.1.19": "sc223 , ms-pa4223",
  "pli-tv-kd11:26.1.22": "sc224 , ms-pa4224",
  "pli-tv-kd11:26.1.35": "sc225 , ms-pa4225",
  "pli-tv-kd11:26.1.37": "sc226 , ms-pa4226",
  "pli-tv-kd11:26.1.42": "sc227 , ms-pa4227",
  "pli-tv-kd11:26.1.45": "sc228 , ms-pa4228",
  "pli-tv-kd11:26.1.48": "sc229 , ms-pa4229",
  "pli-tv-kd11:26.1.53": "sc230 , ms-pa4230",
  "pli-tv-kd11:26.1.56": "sc231 , ms-pa4231",
  "pli-tv-kd11:26.2.1": "sc232 , ms-pa4232",
  "pli-tv-kd11:27.1.1": "sc233, pts-vp-pli2.23 , pts-cs-Kd.11.27.1, ms-pa4233",
  "pli-tv-kd11:27.2.1": "sc234 , ms-pa4234",
  "pli-tv-kd11:28.1.1": "sc235 , pts-vp-en5.33, pts-cs-Kd.11.28.1, ms-pa4235",
  "pli-tv-kd11:28.2.1": "sc236 , pts-cs-Kd.11.28.2, ms-pa4236",
  "pli-tv-kd11:28.2.4": "sc237 , ms-pa4237",
  "pli-tv-kd11:28.2.8": "sc238 , ms-pa4238",
  "pli-tv-kd11:28.2.9": "pts-vp-en5.34",
  "pli-tv-kd11:28.2.11": "sc239, pts-vp-pli2.24 , ms-pa4239",
  "pli-tv-kd11:28.2.12": "pts-vp-pli2.24",
  "pli-tv-kd11:28.2.14": "sc240 , ms-pa4240",
  "pli-tv-kd11:28.2.17": "sc241 , ms-pa4241",
  "pli-tv-kd11:28.2.21": "sc242 , ms-pa4242",
  "pli-tv-kd11:28.2.26": "sc243 , ms-pa4243",
  "pli-tv-kd11:28.3.1": "sc244 , ms-pa4244",
  "pli-tv-kd11:29.1.1": "sc245 , pts-vp-en5.35, pts-cs-Kd.11.29.1, ms-pa4245",
  "pli-tv-kd11:29.1.4": "sc246 , ms-pa4246",
  "pli-tv-kd11:29.1.8": "sc247 , ms-pa4247",
  "pli-tv-kd11:29.1.11": "sc248 , ms-pa4248",
  "pli-tv-kd11:29.1.14": "sc249 , ms-pa4249",
  "pli-tv-kd11:29.1.17": "sc250 , ms-pa4250",
  "pli-tv-kd11:29.1.20": "sc251 , ms-pa4251",
  "pli-tv-kd11:29.1.23": "sc252 , ms-pa4252",
  "pli-tv-kd11:29.2.1": "sc253 , ms-pa4253",
  "pli-tv-kd11:30.1.1": "sc254 , pts-cs-Kd.11.30.1, ms-pa4254",
  "pli-tv-kd11:30.1.7": "sc255 , ms-pa4255",
  "pli-tv-kd11:30.1.11": "sc256 , ms-pa4256",
  "pli-tv-kd11:30.1.16": "sc257 , ms-pa4257",
  "pli-tv-kd11:30.1.23": "sc258 , ms-pa4258",
  "pli-tv-kd11:30.1.25": "sc259 , ms-pa4259",
  "pli-tv-kd11:31.1.1": "sc260, pts-vp-pli2.25 , pts-vp-pli2.25, pts-cs-Kd.11.31.1, ms-pa4260",
  "pli-tv-kd11:31.1.6": "sc261 , ms-pa4261",
  "pli-tv-kd11:31.1.19": "sc262 , ms-pa4262",
  "pli-tv-kd11:31.1.24": "sc263 , ms-pa4263",
  "pli-tv-kd11:31.1.31": "sc264 , ms-pa4264",
  "pli-tv-kd11:31.1.40": "sc265 , ms-pa4265",
  "pli-tv-kd11:31.1.43": "sc266 , ms-pa4266",
  "pli-tv-kd11:31.1.47": "sc267 , ms-pa4267",
  "pli-tv-kd11:31.1.50": "sc268 , ms-pa4268",
  "pli-tv-kd11:31.1.63": "sc269 , ms-pa4269",
  "pli-tv-kd11:31.1.65": "sc270 , ms-pa4270",
  "pli-tv-kd11:31.1.68": "sc271 , ms-pa4271",
  "pli-tv-kd11:31.1.81": "sc272 , ms-pa4272",
  "pli-tv-kd11:31.1.83": "sc273 , ms-pa4273",
  "pli-tv-kd11:31.1.88": "sc274 , ms-pa4274",
  "pli-tv-kd11:31.1.91": "sc275 , ms-pa4275",
  "pli-tv-kd11:31.1.94": "sc276 , ms-pa4276",
  "pli-tv-kd11:31.1.99": "sc277 , ms-pa4277",
  "pli-tv-kd11:31.1.102": "sc278 , ms-pa4278",
  "pli-tv-kd11:31.1.105": "sc279 , ms-pa4279",
  "pli-tv-kd11:31.1.107": "sc280 , ms-pa4280",
  "pli-tv-kd11:31.1.152": "sc281 , ms-pa4281",
  "pli-tv-kd11:31.1.153": "sc282 , ms-pa4282",
  "pli-tv-kd11:31.1.168": "sc283 , ms-pa4283",
  "pli-tv-kd11:31.1.171": "sc284 , ms-pa4284",
  "pli-tv-kd11:31.1.180": "sc285 , ms-pa4285",
  "pli-tv-kd11:31.1.183": "sc286 , ms-pa4286",
  "pli-tv-kd11:31.1.185": "sc287 , ms-pa4287",
  "pli-tv-kd11:31.1.188": "sc288 , ms-pa4288",
  "pli-tv-kd11:31.1.197": "sc289 , ms-pa4289",
  "pli-tv-kd11:31.1.200": "sc290 , ms-pa4290",
  "pli-tv-kd11:31.1.201": "sc291 , ms-pa4291",
  "pli-tv-kd11:31.1.207": "sc292 , ms-pa4292",
  "pli-tv-kd11:31.1.211": "sc293 , ms-pa4293",
  "pli-tv-kd11:31.1.216": "sc294",
  "pli-tv-kd11:31.1.223": "sc295 , ms-pa4295",
  "pli-tv-kd11:31.1.225": "sc296 , ms-pa4296",
  "pli-tv-kd11:32.1.1": "sc297 , pts-cs-Kd.11.32.1, ms-pa4297",
  "pli-tv-kd11:32.1.4": "pts-vp-en5.36",
  "pli-tv-kd11:32.1.6": "sc298 , ms-pa4298",
  "pli-tv-kd11:32.2.1": "sc299, pts-vp-pli2.26 , pts-cs-Kd.11.32.2, ms-pa4299",
  "pli-tv-kd11:32.2.14": "pts-vp-pli2.26",
  "pli-tv-kd11:32.2.18": "sc300 , ms-pa4300",
  "pli-tv-kd11:32.3.1": "pts-vp-en5.37, pts-cs-Kd.11.32.3",
  "pli-tv-kd11:32.3.2": "sc301 , ms-pa4301",
  "pli-tv-kd11:32.3.6": "sc302 , ms-pa4302",
  "pli-tv-kd11:32.4.1": "pts-cs-Kd.11.32.4",
  "pli-tv-kd11:32.4.3": "sc303, pts-vp-pli2.27 , ms-pa4303",
  "pli-tv-kd11:32.4.5": "pts-vp-pli2.27, pts-vp-en5.38",
  "pli-tv-kd11:32.4.10": "sc304 , ms-pa4304",
  "pli-tv-kd11:32.4.19": "sc305 , ms-pa4305",
  "pli-tv-kd11:32.4.30": "sc306 , ms-pa4306",
  "pli-tv-kd11:32.4.33": "sc307 , ms-pa4307",
  "pli-tv-kd11:33.1.1": "sc308 , pts-cs-Kd.11.33.1, ms-pa4308",
  "pli-tv-kd11:33.1.4": "sc309 , ms-pa4309",
  "pli-tv-kd11:33.1.17": "sc310 , ms-pa4310",
  "pli-tv-kd11:33.1.19": "sc311 , ms-pa4311",
  "pli-tv-kd11:33.1.22": "sc312 , ms-pa4312",
  "pli-tv-kd11:33.1.35": "sc313 , ms-pa4313",
  "pli-tv-kd11:33.1.37": "sc314 , ms-pa4314",
  "pli-tv-kd11:33.1.42": "sc315 , ms-pa4315",
  "pli-tv-kd11:33.1.45": "sc316 , ms-pa4316",
  "pli-tv-kd11:33.1.48": "sc317 , ms-pa4317",
  "pli-tv-kd11:33.1.53": "sc318 , ms-pa4318",
  "pli-tv-kd11:33.1.56": "sc319 , ms-pa4319",
  "pli-tv-kd11:33.1.59": "sc320 , ms-pa4320",
  "pli-tv-kd11:33.1.61": "sc321 , ms-pa4321",
  "pli-tv-kd11:33.1.106": "sc322 , ms-pa4322",
  "pli-tv-kd11:34.1.1": "sc323 , pts-cs-Kd.11.34.1, ms-pa4323",
  "pli-tv-kd11:34.1.5": "pts-vp-en5.39",
  "pli-tv-kd11:34.1.7": "sc324, pts-vp-pli2.28 , ms-pa4324",
  "pli-tv-kd11:34.1.9": "pts-vp-pli2.28",
  "pli-tv-kd11:34.2.1": "sc325 , pts-cs-Kd.11.34.2, ms-pa4325",
  "pli-tv-kd11:34.2.4": "sc326 , ms-pa4326",
  "pli-tv-kd11:34.2.9": "sc327 , ms-pa4327",
  "pli-tv-kd11:34.2.12": "sc328 , ms-pa4328",
  "pli-tv-kd11:34.2.14": "sc329 , ms-pa4329",
  "pli-tv-kd11:34.2.17": "sc330 , ms-pa4330",
  "pli-tv-kd11:34.2.22": "sc331 , ms-pa4331",
  "pli-tv-kd11:34.3.1": "sc332 , ms-pa4332",
  "pli-tv-kd11:35.1.1": "sc333 , pts-cs-Kd.11.35.1, ms-pa4333",
  "pli-tv-kd11:35.1.7": "sc334 , ms-pa4334",
  "pli-tv-kd11:35.1.11": "sc335 , ms-pa4335",
  "pli-tv-kd11:35.1.16": "sc336 , ms-pa4336",
  "pli-tv-kd11:35.1.23": "sc337 , ms-pa4337",
  "pli-tv-kd11:35.1.25": "sc338 , ms-pa4338",
  "pli-tv-kd11:35.1.27": "sc339 , pts-vp-pli2.29-30, pts-vp-en5.40-43, ms-pa4339-372",
  "pli-tv-kd11:35.1.28": "sc340",
  "pli-tv-kd11:35.1.32": "sc341",
  "pli-tv-kd11:35.1.36": "sc342",
  "pli-tv-kd11:35.1.40": "sc343",
  "pli-tv-kd11:35.1.44": "sc344",
  "pli-tv-kd11:35.1.48": "sc345",
  "pli-tv-kd11:35.1.52": "sc346",
  "pli-tv-kd11:35.1.56": "sc347, pts-vp-pli2.29",
  "pli-tv-kd11:35.1.60": "sc348",
  "pli-tv-kd11:35.1.64": "sc349",
  "pli-tv-kd11:35.1.68": "sc350",
  "pli-tv-kd11:35.1.72": "sc351",
  "pli-tv-kd11:35.1.76": "sc352",
  "pli-tv-kd11:35.1.80": "sc353",
  "pli-tv-kd11:35.1.84": "sc354",
  "pli-tv-kd11:35.1.88": "sc355",
  "pli-tv-kd11:35.1.92": "sc356",
  "pli-tv-kd11:35.1.96": "sc357",
  "pli-tv-kd11:35.1.100": "sc358",
  "pli-tv-kd11:35.1.104": "sc359",
  "pli-tv-kd11:35.1.108": "sc360",
  "pli-tv-kd11:35.1.112": "sc361",
  "pli-tv-kd11:35.1.116": "sc362",
  "pli-tv-kd11:35.1.120": "sc363",
  "pli-tv-kd11:35.1.126": "sc364",
  "pli-tv-kd11:35.1.130": "sc365, pts-vp-pli2.30",
  "pli-tv-kd11:35.1.134": "sc366",
  "pli-tv-kd11:35.1.138": "sc367",
  "pli-tv-kd11:35.1.142": "sc368",
  "pli-tv-kd11:35.1.146": "sc369",
  "pli-tv-kd11:35.1.150": "sc370",
  "pli-tv-kd11:35.1.154": "sc371",
  "pli-tv-kd11:35.1.158": "sc372",
  "pli-tv-kd11:35.1.162": "sc373 , ms-pa4373"
}