{
  "ne5:5.1": "sc1",
  "ne5:6.1": "sc2",
  "ne5:7.1": "sc3",
  "ne5:8.1": "sc4,  pts11",
  "ne5:9.1": "sc5",
  "ne5:10.1": "sc6",
  "ne5:11.1": "sc7",
  "ne5:12.1": "sc8",
  "ne5:13.1": "sc9",
  "ne5:14.1": "sc10",
  "ne5:15.1": "sc11,  pts12",
  "ne5:16.1": "sc12",
  "ne5:17.1": "sc13",
  "ne5:18.1": "sc14",
  "ne5:19.1": "sc15",
  "ne5:20.1": "sc16",
  "ne5:21.1": "sc17,  pts13",
  "ne5:22.1": "sc18",
  "ne5:23.1": "sc19",
  "ne5:24.1": "sc20",
  "ne5:25.1": "sc21",
  "ne5:26.1": "sc22",
  "ne5:27.1": "sc23,  pts14",
  "ne5:28.1": "sc24",
  "ne5:29.1": "sc25",
  "ne5:30.1": "sc26",
  "ne5:31.1": "sc27",
  "ne5:32.1": "sc28,  pts15",
  "ne5:33.1": "sc29",
  "ne5:34.1": "sc30",
  "ne5:35.1": "sc31",
  "ne5:36.1": "sc32,  pts16",
  "ne5:37.1": "sc33",
  "ne5:38.1": "sc34",
  "ne5:39.1": "sc35,  pts17",
  "ne5:40.1": "sc36",
  "ne5:41.1": "sc37",
  "ne5:42.1": "sc38",
  "ne5:43.1": "sc39",
  "ne5:44.1": "sc40",
  "ne5:45.1": "sc41",
  "ne5:46.1": "sc42,  pts18",
  "ne5:47.1": "sc43",
  "ne5:48.1": "sc44",
  "ne5:49.1": "sc45,  pts19",
  "ne5:50.1": "sc46",
  "ne5:51.1": "sc47",
  "ne5:52.1": "sc48",
  "ne5:53.1": "sc49,  pts20",
  "ne5:54.1": "sc50",
  "ne5:55.1": "sc51",
  "ne5:56.1": "sc52,  pts21",
  "ne5:57.1": "sc53",
  "ne5:58.1": "sc54"
}