{
  "vv84:5.1": "sc1,  vns969,  pts2ed126",
  "vv84:6.1": "sc2,  vns970",
  "vv84:7.1": "sc3,  vns971",
  "vv84:8.1": "sc4,  vns972",
  "vv84:9.1": "sc5,  vns973",
  "vv84:10.1": "sc6,  vns974",
  "vv84:11.1": "sc7,  vns975",
  "vv84:12.1": "sc8,  vns976,  pts2ed127",
  "vv84:13.1": "sc9,  vns977",
  "vv84:14.1": "sc10,  vns978",
  "vv84:15.1": "sc11,  vns979",
  "vv84:16.1": "sc12,  vns980",
  "vv84:17.1": "sc13,  vns981",
  "vv84:18.1": "sc14,  vns982",
  "vv84:19.1": "sc15,  vns983",
  "vv84:20.1": "sc16,  vns984",
  "vv84:21.1": "sc17,  vns985",
  "vv84:22.1": "sc18,  vns986,  pts2ed128",
  "vv84:23.1": "sc19,  vns987",
  "vv84:24.1": "sc20,  vns988",
  "vv84:25.1": "sc21,  vns989",
  "vv84:26.1": "sc22,  vns990",
  "vv84:27.1": "sc23,  vns991",
  "vv84:28.1": "sc24,  vns992",
  "vv84:29.1": "sc25,  vns993",
  "vv84:30.1": "sc26,  vns994",
  "vv84:31.1": "sc27,  vns995,  pts2ed129",
  "vv84:32.1": "sc28,  vns996",
  "vv84:33.1": "sc29,  vns997",
  "vv84:34.1": "sc30,  vns998",
  "vv84:35.1": "sc31,  vns999",
  "vv84:36.1": "sc32,  vns1000",
  "vv84:37.1": "sc33,  vns1001",
  "vv84:38.1": "sc34,  vns1002",
  "vv84:39.1": "sc35,  vns1003",
  "vv84:40.1": "sc36,  vns1004",
  "vv84:41.1": "sc37,  vns1005,  pts2ed130",
  "vv84:42.1": "sc38,  vns1006",
  "vv84:43.1": "sc39,  vns1007",
  "vv84:44.1": "sc40,  vns1008",
  "vv84:45.1": "sc41,  vns1009",
  "vv84:46.1": "sc42,  vns1010",
  "vv84:47.1": "sc43,  vns1011",
  "vv84:48.1": "sc44,  vns1012",
  "vv84:49.1": "sc45,  vns1013",
  "vv84:50.1": "sc46,  vns1014,  pts2ed131",
  "vv84:51.1": "sc47,  vns1015",
  "vv84:52.1": "sc48,  vns1016",
  "vv84:53.1": "sc49,  vns1017",
  "vv84:54.1": "sc50,  vns1018",
  "vv84:55.1": "sc51,  vns1019",
  "vv84:56.1": "sc52,  vns1020",
  "vv84:57.1": "sc53,  vns1021",
  "vv84:58.1": "sc54,  vns1022",
  "vv84:59.1": "sc55"
}