{
  "pli-tv-bi-vb-pj6:5.1": "sc1, pts-vp-pli4.216, pts-cs-Bi-Pj.2.1, pts-vp-pli4.216, pts-vp-en3.165, ms-pa2139",
  "pli-tv-bi-vb-pj6:6.1": "sc2, ms-pa2140",
  "pli-tv-bi-vb-pj6:6.5": "pts-vp-en3.166",
  "pli-tv-bi-vb-pj6:7.1": "sc3, pts-vp-pli4.217, ms-pa2141, pts-vp-pli4.217",
  "pli-tv-bi-vb-pj6:8.1": "sc4, pts-cs-Bi-Pj.2.2.1, ms-pa2142",
  "pli-tv-bi-vb-pj6:9.1": "sc5, ms-pa2143",
  "pli-tv-bi-vb-pj6:10.1": "sc6, ms-pa2144",
  "pli-tv-bi-vb-pj6:11.1": "sc7, ms-pa2145",
  "pli-tv-bi-vb-pj6:12.1": "sc8, ms-pa2146",
  "pli-tv-bi-vb-pj6:13.1": "sc9, pts-vp-en3.167, ms-pa2147",
  "pli-tv-bi-vb-pj6:13.10": "sc10, ms-pa2148",
  "pli-tv-bi-vb-pj6:15.1": "sc11, ms-pa2149",
  "pli-tv-bi-vb-pj6:16.1": "sc12, ms-pa2150",
  "pli-tv-bi-vb-pj6:17.1": "sc13, ms-pa2151",
  "pli-tv-bi-vb-pj6:18.1": "sc14, ms-pa2152",
  "pli-tv-bi-vb-pj6:19.1": "sc15, pts-cs-Bi-Pj.2.2.2, ms-pa2153, pts-vp-en3.168",
  "pli-tv-bi-vb-pj6:20.1": "sc16, ms-pa2154"
}