{
  "pli-tv-kd8:1.1.2": "phitā → phītā (s1-3, pts1)",
  "pli-tv-kd8:1.1.7": "ambapālī ca → ambapālikā (pts1) | padakkhiṇā → padakkhā (s1-3)",
  "pli-tv-kd8:1.2.1": "rājagahako → rājagahiko (bj)",
  "pli-tv-kd8:1.2.7": "padakkhiṇaṃ → padakkhaṃ (s1-3) | upasobhantiṃ → upasobhitaṃ (bj); upasobhitanti (pts1)",
  "pli-tv-kd8:1.2.13": "vuṭṭhāpessāmā”ti → vuṭṭhāpeyyāmāti (bj, s1-3, pts1, mr)",
  "pli-tv-kd8:1.3.1": "kumārī → kumārikā (bj)",
  "pli-tv-kd8:1.3.6": "amanāpā → amanāpā hoti (bj)",
  "pli-tv-kd8:1.3.8": "sakkāro bhañjissati → parihāyissati (bj, s1-3, pts1)",
  "pli-tv-kd8:1.4.5": "abhayo nāma rājakumāro → abhayo rājakumāro (bj)",
  "pli-tv-kd8:1.5.6": "mayāsi → mayāpi (s1-3, pts1, mr)",
  "pli-tv-kd8:1.5.10": "takkasilāyaṃ → takkasīlāyaṃ (mr)",
  "pli-tv-kd8:1.6.5": "na sammussati → na pamussati (bj, s1-3, pts1)",
  "pli-tv-kd8:1.7.7": "yojanaṃ, na kiñci → āhiṇṭanto na kiñci (mr)",
  "pli-tv-kd8:1.7.8": "Susikkhitosi → sikkhitosi (bj, s1-3, pts1)",
  "pli-tv-kd8:1.11.2": "pasatena → pasatena me (bj, s1-3)",
  "pli-tv-kd8:1.11.4": "nipātetvā → nipajjāpetvā (bj, s1-3, pts1)",
  "pli-tv-kd8:1.12.2": "acchariyaṃ → acchariyaṃ vata bho (s1-3)",
  "pli-tv-kd8:1.12.3": "Bahukāni ca me mahagghāni → mahagghāni mahagghāni (bj, s1-3, pts1)",
  "pli-tv-kd8:1.12.4": "kiñci → kañci (s1-3)",
  "pli-tv-kd8:1.12.11": "āgārikā → agārikā (bj, pts1)",
  "pli-tv-kd8:1.13.4": "arogā ṭhitā”ti → arogāpitāti (bj)",
  "pli-tv-kd8:1.14.4": "na ciraṃ → nacirasseva (s1-3, pts1)",
  "pli-tv-kd8:1.14.7": "maṃ disvā → deviyo disvā (bj, s1-3, pts1)",
  "pli-tv-kd8:1.15.4": "passāmā”ti → passāmīti (s1-3)",
  "pli-tv-kd8:1.15.9": "bhikkhusaṃghan”ti → saṅghanti (bj); bhikkhusaṅghañcāti (s1-3, pts1)",
  "pli-tv-kd8:1.16.10": "bahūpakāro → bahukāro (bj)",
  "pli-tv-kd8:1.17.12": "sace tvaṃ, gahapati, arogo bhaveyyāsi → sacāhaṃ taṃ gahapati arogāpeyyaṃ (bj, pts1); sacāhantaṃ gahapati arogaṃ kareyyaṃ (s1-3)",
  "pli-tv-kd8:1.18.7": "mañcake → mañcakena (bj) | uppāṭetvā → phāletvā (bj) | upphāletvā (pts1) | nipātetvā → nipajjāpetvā (bj, s1-3, pts1) | sibbiniṃ → sibbaniṃ (bj) | mahājanassa → janassa (bj, s1-3, pts1)",
  "pli-tv-kd8:1.18.8": "passathayye → passesyātha (bj); passatha (s1-3); passathayyo (pts1, mr)",
  "pli-tv-kd8:1.18.21": "sibbitvā → sibbetvā (bj, s1-3, pts1)",
  "pli-tv-kd8:1.19.8": "ācariya, sakkomi → nāhaṃ sakkomi (bj, s1-3)",
  "pli-tv-kd8:1.20.4": "Jānāsi → jānābhi (bj); jānāhi (s1-3, pts1)",
  "pli-tv-kd8:1.22.3": "ubbandhitvā → upanibandhitvā (bj, s1-3) | tirokaraṇiyaṃ → tirokaraṇiṃ (bj, s1-3)",
  "pli-tv-kd8:1.22.9": "arogo ṭhito”ti → arogāpitoti (bj)",
  "pli-tv-kd8:1.23.1": "samayena rañño → ujjeniyaṃ rañño (s1-3)",
  "pli-tv-kd8:1.24.1": "dehi → idaṃ padadvayaṃ bj, s1-3 potthakesu",
  "pli-tv-kd8:1.25.7": "sappiṃ → taṃ sappiṃ (s1-3)",
  "pli-tv-kd8:1.26.6": "amanussena paṭicca jāto → amanussena jāto (bj)",
  "pli-tv-kd8:1.27.4": "bhuñjāma → bhuñjāmi (bj, s1-3)",
  "pli-tv-kd8:1.28.8": "hatthinikaṃ kākassa niyyādetvā yena → yena rājagahaṃ yena (bj, s1-3, pts1)",
  "pli-tv-kd8:1.29.3": "ayyo → deva (s1-3)",
  "pli-tv-kd8:1.29.6": "bahūnaṃ → bahunnaṃ (bj, s1-3)",
  "pli-tv-kd8:1.33.17": "alaṃ yūsapiṇḍapātenā”ti → alaṃ tāva yūsapiṇḍapātenāti (bj); alaṃ yūsapiṇḍakenāti (s1-3)",
  "pli-tv-kd8:1.35.5": "Itarītarenapāhaṃ → pahaṃ (bj); cāhaṃ (s1-3)",
  "pli-tv-kd8:9.4.2": "dātabbo, āgatapaṭipāṭiyā → āgatāgatapaṭipāṭiyā (mr)",
  "pli-tv-kd8:10.2.1": "sītudakāya → sītundikāya (bj); sītūdakāya (s1-3); sītunnakāya (pts1)",
  "pli-tv-kd8:10.2.7": "uttarāḷumpaṃ → uttarāḷuvaṃ (s1-3); uttarāḷupaṃ (yojanā)",
  "pli-tv-kd8:10.3.1": "āviñchanti → āviñjanti (bj); āvaṭṭanti (s1-3); āvajjanti (pts1)",
  "pli-tv-kd8:10.3.4": "rajanuḷuṅkaṃ → rajanauluṅkaṃ (pts1); rajanāḷuṅkaṃ (yojanā)",
  "pli-tv-kd8:11.2.9": "seyyathāpi nāma → seyyathāpi (?)",
  "pli-tv-kd8:12.1.2": "acchibaddhaṃ → accibaddhaṃ (bj, s1-3); accibandhaṃ (pts1); acchibandhaṃ (mr)",
  "pli-tv-kd8:12.1.9": "passatu me → passatha tumhe (mr)",
  "pli-tv-kd8:13.1.2": "ubbhaṇḍite → ubbhaṇḍīkate (s1-3)",
  "pli-tv-kd8:14.2.2": "acchupentaṃ → acchupantaṃ (mr)",
  "pli-tv-kd8:15.4.1": "gattāni sītiṃ karitvā → sītīkaritvā (s1, pts1); sītikaritvā (s2)",
  "pli-tv-kd8:15.5.2": "sandahatha → sannahatha (bj, s1-3, pts1)",
  "pli-tv-kd8:15.5.5": "samiñjitaṃ → sammiñjitaṃ (s1-3, pts1)",
  "pli-tv-kd8:15.6.2": "pavattamānesu, na hi nāma ekabhikkhussapi → vattamānesu na hi nāma ekabhikkhussāpi (s1-3); pavattamānesu na ekabhikkhussapi (?)",
  "pli-tv-kd8:15.11.3": "tumhākaṃ, ayye, daharānaṃ → daharānaṃ daharānaṃ (bj)",
  "pli-tv-kd8:15.14.9": "Dibbaṃ sā labhate āyuṃ → dibbaṃ balaṃ sā labhate ca āyuṃ (bj, s1-3)",
  "pli-tv-kd8:18.1.1": "mukhapuñchanacoḷaṃ → mukhapuñchanacolaṃ (s1-3); mukhapuñchanacolakaṃ (pts1); mukhapuñjanacoḷaṃ (mr)",
  "pli-tv-kd8:18.1.8": "mukhapuñchanacoḷakan”ti → mukhapuñchanacolanti (s1-3); mukhapuñchanacolakanti (pts1)",
  "pli-tv-kd8:22.1.4": "Mātāpitaroti → mātāpitūnaṃ kho (bj) | mātāpitaro hi (pts1) | dadamāne → vadamāno (mr); vadamāne (?)",
  "pli-tv-kd8:23.1.6": "Idhāhaṃ → so ahaṃ (katthaci)",
  "pli-tv-kd8:28.1.3": "dhutatāya → dhūtattāya (s1-3); dhutattāya (pts1, mr)",
  "pli-tv-kd8:29.1.4": "sabbamañjiṭṭhakāni → sabbamañjeṭṭhakāni (bj, s1-3, pts1)",
  "pli-tv-kd8:29.1.11": "phaṇadasāni → phaladasāni (mr)",
  "pli-tv-kd8:32.1.58": "sītudakā → sītundī ca (bj); situṇhaṃ ca (s1); sītuṇhaṃ ca (s2, s3); sītuṇhi ca (pts1)",
  "pli-tv-kd8:32.1.87": "gilānakā → gilāyanā (s1-3, pts1, mr)"
}