{
  "ps2.1:4.1": "sc1,  pts2.92",
  "ps2.1:5.1": "sc2",
  "ps2.1:6.1": "sc3",
  "ps2.1:7.1": "sc4",
  "ps2.1:8.1": "sc5,  pts2.93",
  "ps2.1:9.1": "sc6",
  "ps2.1:10.1": "sc7",
  "ps2.1:12.1": "sc8",
  "ps2.1:13.1": "sc9",
  "ps2.1:14.1": "sc10,  pts2.94",
  "ps2.1:15.1": "sc11",
  "ps2.1:16.1": "sc12",
  "ps2.1:17.1": "sc13,  pts2.95",
  "ps2.1:18.1": "sc14",
  "ps2.1:19.1": "sc15",
  "ps2.1:20.1": "sc16",
  "ps2.1:21.1": "sc17,  pts2.96",
  "ps2.1:22.1": "sc18",
  "ps2.1:23.1": "sc19",
  "ps2.1:24.1": "sc20,  pts2.97",
  "ps2.1:25.1": "sc21",
  "ps2.1:26.1": "sc22",
  "ps2.1:27.1": "sc23,  pts2.98",
  "ps2.1:28.1": "sc24",
  "ps2.1:29.1": "sc25",
  "ps2.1:30.1": "sc26",
  "ps2.1:31.1": "sc27",
  "ps2.1:32.1": "sc28,  pts2.99",
  "ps2.1:33.1": "sc29",
  "ps2.1:34.1": "sc30",
  "ps2.1:35.1": "sc31",
  "ps2.1:36.1": "sc32",
  "ps2.1:37.1": "sc33,  pts2.100",
  "ps2.1:38.1": "sc34",
  "ps2.1:39.1": "sc35",
  "ps2.1:42.1": "sc36,  pts2.101",
  "ps2.1:43.1": "sc37",
  "ps2.1:44.1": "sc38,  pts2.102",
  "ps2.1:45.1": "sc39",
  "ps2.1:46.1": "sc40",
  "ps2.1:47.1": "sc41",
  "ps2.1:48.1": "sc42",
  "ps2.1:49.1": "sc43,  pts2.103",
  "ps2.1:50.1": "sc44",
  "ps2.1:51.1": "sc45"
}