{
  "an3.64:1.4": [
    "parisati → parisatiṃ (bj, pts1)"
  ],
  "an3.64:2.6": [
    "sippinikātīraṃ → sappinikātīraṃ (bj, pts1) | sappiniyā tīraṃ (s1-3, km)"
  ],
  "an3.64:5.2": [
    "yo → etthantare pāṭho sī potthake",
    "mayā (s1-3, km, pts1)"
  ],
  "an3.64:8.1": [
    "paribbājakā → paribbājako (mr)"
  ],
  "an3.64:8.3": [
    "nāññataraṃ → aññataraṃ (mr)",
    "tuṇhībhūto maṅkubhūto → tuṇhībhūto vā maṅkubhūto (bj, s1-3, km) | tuṇhībhūto vā maṅkubhūto vā (pts1)"
  ],
  "an3.64:11.1": [
    "vācāyasannitodakena → vācāsattitodakena (bj)"
  ],
  "an3.64:11.2": [
    "siṅgālakaṃyeva → segālakaṃyeva (bj, s1-3, km, pts1)",
    "bheraṇḍakaṃyeva → bhedaṇḍakaṃ (mr)"
  ],
  "an3.64:11.4": [
    "ambukasañcarī → ambakamaddarī (bj, s1-3, pts1)",
    "purisakaravitaṃ → phussakaravitaṃ (bj, pts1) | pussakaravitaṃ (s1-3, km)"
  ]
}