{
  "ne5:6.2": "visajjanaṃ → vissajjanaṃ (bj, pts-vp-pli1ed, mr)",
  "ne5:10.2": "Vivicchā → vevicchā (^snp5.2#87 [Ajitamāṇavapucchā])",
  "ne5:14.1": "pakāsanti → pakāsenti (^dhp290-305#297.1 [290. Attanopubbakammavatthu/297. Cūḷasubhaddāvatthu])",
  "ne5:14.4": "rattiṃ khittā → rattikhittā (bj, pts-vp-pli1ed)",
  "ne5:17.3": "Andhantamaṃ → andhatamaṃ (pts-vp-pli1ed, mr)",
  "ne5:20.4": "pidhīyare → pithīyareti (bj) | pidhiyyare (pts-vp-pli1ed, mr)",
  "ne5:23.2": "amanāpikesu → amanāpiyesu (mr)",
  "ne5:28.2": "Kissa → tassa (bj)",
  "ne5:30.1": "apucchi → āpucchi (bj) | maṃ pucchi (mr)",
  "ne5:31.1": "pañhe → pañho (bj, pts-vp-pli1ed, mr)",
  "ne5:31.6": "avijjāvasesā → avijjā ca niravasesā (bj, pts-vp-pli1ed, mr)",
  "ne5:38.3": "rattiṃ → ratti (pts-vp-pli1ed, mr)",
  "ne5:39.4": "nibbattayati → nibbattiyati (mr)",
  "ne5:49.1": "Katame → katame ca (bj)",
  "ne5:54.2": "nibbattenti → nibbattayanti (pts-vp-pli1ed) | nibbattāpenti (mr)",
  "ne5:56.1": "samiñjite → sammiñjite (bj, pts-vp-pli1ed)",
  "ne5:58.2": "samānetabbā → samānayitabbā (bj, pts-vp-pli1ed, mr)"
}