{
  "cnd19:5.1": "sc1",
  "cnd19:6.1": "sc2",
  "cnd19:7.1": "sc3",
  "cnd19:8.1": "sc4",
  "cnd19:9.1": "sc5",
  "cnd19:10.1": "sc6",
  "cnd19:11.1": "sc7",
  "cnd19:12.1": "sc8",
  "cnd19:13.1": "sc9",
  "cnd19:14.1": "sc10",
  "cnd19:15.1": "sc11",
  "cnd19:16.1": "sc12",
  "cnd19:17.1": "sc13",
  "cnd19:18.1": "sc14",
  "cnd19:19.1": "sc15",
  "cnd19:20.1": "sc16",
  "cnd19:21.1": "sc17",
  "cnd19:22.1": "sc18",
  "cnd19:23.1": "sc19",
  "cnd19:24.1": "sc20",
  "cnd19:25.1": "sc21",
  "cnd19:26.1": "sc22",
  "cnd19:27.1": "sc23",
  "cnd19:28.1": "sc24",
  "cnd19:29.1": "sc25",
  "cnd19:30.1": "sc26",
  "cnd19:31.1": "sc27",
  "cnd19:32.1": "sc28",
  "cnd19:33.1": "sc29",
  "cnd19:34.1": "sc30",
  "cnd19:35.1": "sc31",
  "cnd19:36.1": "sc32",
  "cnd19:37.1": "sc33",
  "cnd19:38.1": "sc34",
  "cnd19:39.1": "sc35",
  "cnd19:40.1": "sc36",
  "cnd19:41.1": "sc37",
  "cnd19:42.1": "sc38",
  "cnd19:43.1": "sc39",
  "cnd19:44.1": "sc40",
  "cnd19:45.1": "sc41",
  "cnd19:46.1": "sc42",
  "cnd19:47.1": "sc43",
  "cnd19:48.1": "sc44",
  "cnd19:49.1": "sc45",
  "cnd19:50.1": "sc46",
  "cnd19:51.1": "sc47",
  "cnd19:52.1": "sc48",
  "cnd19:53.1": "sc49",
  "cnd19:54.1": "sc50",
  "cnd19:55.1": "sc51",
  "cnd19:56.1": "sc52",
  "cnd19:57.1": "sc53",
  "cnd19:58.1": "sc54",
  "cnd19:59.1": "sc55",
  "cnd19:60.1": "sc56",
  "cnd19:61.1": "sc57",
  "cnd19:62.1": "sc58",
  "cnd19:63.1": "sc59",
  "cnd19:64.1": "sc60",
  "cnd19:65.1": "sc61",
  "cnd19:66.1": "sc62",
  "cnd19:67.1": "sc63",
  "cnd19:68.1": "sc64",
  "cnd19:69.1": "sc65",
  "cnd19:70.1": "sc66",
  "cnd19:71.1": "sc67",
  "cnd19:72.1": "sc68"
}