{
  "cnd16:5.1": "sc1",
  "cnd16:6.1": "sc2",
  "cnd16:7.1": "sc3",
  "cnd16:8.1": "sc4",
  "cnd16:9.1": "sc5",
  "cnd16:10.1": "sc6",
  "cnd16:11.1": "sc7",
  "cnd16:12.1": "sc8",
  "cnd16:13.1": "sc9",
  "cnd16:14.1": "sc10",
  "cnd16:15.1": "sc11",
  "cnd16:16.1": "sc12",
  "cnd16:17.1": "sc13",
  "cnd16:18.1": "sc14",
  "cnd16:19.1": "sc15",
  "cnd16:20.1": "sc16",
  "cnd16:21.1": "sc17",
  "cnd16:22.1": "sc18",
  "cnd16:23.1": "sc19",
  "cnd16:24.1": "sc20",
  "cnd16:25.1": "sc21",
  "cnd16:26.1": "sc22",
  "cnd16:27.1": "sc23",
  "cnd16:28.1": "sc24",
  "cnd16:29.1": "sc25",
  "cnd16:30.1": "sc26",
  "cnd16:31.1": "sc27",
  "cnd16:32.1": "sc28"
}