{
  "kv2.5:1.1": "ms32Kv_933, msdiv326, sc1",
  "kv2.5:2.1": "ms32Kv_934, sc2",
  "kv2.5:3.1": "ms32Kv_935, sc3",
  "kv2.5:4.1": "ms32Kv_936, sc4",
  "kv2.5:5.1": "ms32Kv_937, sc5",
  "kv2.5:6.1": "ms32Kv_938, pts-vp-pli196, sc6",
  "kv2.5:7.1": "ms32Kv_939, sc7",
  "kv2.5:8.1": "ms32Kv_940, sc8",
  "kv2.5:9.1": "ms32Kv_941, msdiv327, sc9",
  "kv2.5:10.1": "ms32Kv_942, sc10",
  "kv2.5:11.1": "ms32Kv_943, sc11",
  "kv2.5:12.1": "ms32Kv_944, sc12",
  "kv2.5:13.1": "ms32Kv_945, sc13",
  "kv2.5:14.1": "ms32Kv_946, sc14",
  "kv2.5:15.1": "ms32Kv_947, msdiv328, pts-vp-pli197, sc15",
  "kv2.5:16.1": "ms32Kv_948, sc16",
  "kv2.5:17.1": "ms32Kv_949, sc17",
  "kv2.5:18.1": "ms32Kv_950, sc18",
  "kv2.5:19.1": "ms32Kv_951, msdiv329, sc19",
  "kv2.5:20.1": "ms32Kv_952, sc20",
  "kv2.5:21.1": "ms32Kv_953, pts-vp-pli198, sc21",
  "kv2.5:22.1": "ms32Kv_954, sc22",
  "kv2.5:23.1": "ms32Kv_955, sc23",
  "kv2.5:24.1": "ms32Kv_956, sc24",
  "kv2.5:25.1": "ms32Kv_957, sc25",
  "kv2.5:26.1": "ms32Kv_958, pts-vp-pli199, sc26",
  "kv2.5:27.1": "ms32Kv_959, sc27",
  "kv2.5:28.1": "ms32Kv_960, msdiv330, sc28",
  "kv2.5:29.1": "ms32Kv_961, sc29",
  "kv2.5:30.1": "ms32Kv_962, sc30",
  "kv2.5:31.1": "ms32Kv_963, sc31",
  "kv2.5:32.1": "ms32Kv_964, msdiv331, pts-vp-pli200, sc32",
  "kv2.5:33.1": "ms32Kv_965, sc33",
  "kv2.5:34.1": "ms32Kv_966, sc34",
  "kv2.5:35.1": "ms32Kv_967, sc35",
  "kv2.5:36.1": "ms32Kv_968, msdiv332, sc36",
  "kv2.5:37.1": "ms32Kv_969, sc37",
  "kv2.5:38.1": "ms32Kv_970, pts-vp-pli201, sc38",
  "kv2.5:39.1": "ms32Kv_971, sc39",
  "kv2.5:40.1": "ms32Kv_972, sc40",
  "kv2.5:41.1": "ms32Kv_973, sc41",
  "kv2.5:42.1": "ms32Kv_974, msdiv333, pts-vp-pli202, sc42",
  "kv2.5:43.1": "ms32Kv_975, sc43",
  "kv2.5:44.1": "ms32Kv_976, sc44",
  "kv2.5:45.1": "ms32Kv_977, sc45",
  "kv2.5:46.1": "ms32Kv_978, pts-vp-pli203, sc46",
  "kv2.5:47.1": "ms32Kv_979, sc47",
  "kv2.5:48.1": "ms32Kv_980, sc48",
  "kv2.5:49.1": "ms32Kv_981, sc49",
  "kv2.5:50.1": "ms32Kv_982, sc50",
  "kv2.5:50.4": "ms32Kv_983"
}