{
  "dn3:1.2.1": "pokkharasāti → pokkharasātī (bj) | pokkharasādi (pts1)",
  "dn3:1.2.5": "bhagavā → bhagavāti (s1-3, km)",
  "dn3:1.3.1": "vedānaṃ → bedānaṃ (mr)",
  "dn3:1.9.3": "kañci kañci → kiñci kiñci (c1)",
  "dn3:1.10.6": "kaṇhā → kiṇhā (pts1, mr)",
  "dn3:1.11.1": "āgaccheyyātha → āgaccheyyātho (bj, pts1), manasi kareyyātha → manasi kareyyātho (bj, pts1)",
  "dn3:1.12.7": "garuṃ karonti → garukaronti (bj, s1-3, km, pts1)",
  "dn3:1.13.4": "sandhāgāre → santhāgāre (bj, pts1)",
  "dn3:1.15.9": "karakaṇḍaṃ → karakaṇḍuṃ (s1-3) | karaṇḍuṃ (pts1), sinisūraṃ → nipuraṃ (bj) | sinipuraṃ (s1-3) | sīnipuraṃ (pts1), okkāmukhaṃ → ukkāmukhaṃ (bj, s1-3)",
  "dn3:1.16.2": "kaṇhaṃ nāma → sā kaṇhaṃ (pts1)",
  "dn3:1.18.3": "mantavho → mantayavho (bj)",
  "dn3:1.21.1": "sajotibhūtaṃ → saṃjotibhūtaṃ (s1-3)",
  "dn3:1.21.5": "kimetaṃ → kiṃ me taṃ (bj, mr)",
  "dn3:1.21.6": "bravitū”ti → brūtūti (s1-3) | brūmetūti (pts1)",
  "dn3:1.23.8": "sannayhi → sannahi (mr)",
  "dn3:1.23.11": "bhaddante → bhadante (bj, s1-3, pts1)",
  "dn3:1.28.1": "Brahmunā pesā, ambaṭṭha → brahmunāpi ambaṭṭha (bj, mr) | brahmunā cesā ambaṭṭha (s1-3) | brahmunāpi esā ambaṭṭha (pts1)",
  "dn3:2.3.7": "kudālapiṭakaṃ → kuddālapiṭakaṃ (bj, s1-3, pts1)",
  "dn3:2.8.1": "yamataggi → yamataggī (s1-3) | yamadaggi (mr)",
  "dn3:2.10.11": "dīghāsivudhehi → dīghāsi­bad­dhehi (bj, s1-3, pts1)",
  "dn3:2.14.11": "yāvatako → yāvatiko (mr)",
  "dn3:2.15.2": "tevijjaka → tevijjakā (mr)",
  "dn3:2.15.4": "kupito → so kupito (pts1)",
  "dn3:2.16.3": "Svedāni → dāni sve (mr)",
  "dn3:2.17.2": "te → tedha (s1-3) | te idha (pts1)"
}