{
  "cnd10:5.3": "Ārammaṇaṃ → āramaṇaṃ (mr)",
  "cnd10:9.1": "ārammaṇaṃ ālambaṇaṃ → ārammaṇanti ālambanaṃ (bj) | ārammaṇaṃ brūhīti ārammaṇaṃ ālambaṇaṃ (sya-all)",
  "cnd10:9.3": "samupāgato → samupagato (bj), samupapanno → sampanno (bj)",
  "cnd10:14.4": "nattamahābhipassa → rattamahābhipassa (sya-all)",
  "cnd10:15.1": "ākiñcaññāyatanasamāpattiṃ lābhīyeva → ... samāpattilābhī santaṃyeva (bj)",
  "cnd10:18.1": "nissāya → taṃ nissāya (bj, sya-all)",
  "cnd10:18.3": "vibhāveti → vyabhāveti (bj)",
  "cnd10:18.4": "ālambaṇaṃ → ālambanaṃ (bj) | ārammaṇaṃ ālambaṇaṃ (sya-all)",
  "cnd10:19.13": "vippamutto → vippayutto (bj)",
  "cnd10:20.1": "ti → rattamahābhipassāti (sya-all)",
  "cnd10:20.5": "vuccati ratti → rattanti ratti (sya-all)",
  "cnd10:22.3": "paramedhimutto → parame vimutto (^snp5.7#669 [Upasīvamāṇavapucchā])",
  "cnd10:25.2": "allīno → assito allīno (bj)",
  "cnd10:26.2": "Tāsaṃ saññāsamāpattīnaṃ → yāvatā saññāsamāpattī tāsaṃ (bj), ākiñcaññāyatanasamāpattivimokkho → ... vimokkhā (sya-all, mr)",
  "cnd10:27.5": "aviccamāno → avedhamāno (sya-all)",
  "cnd10:36.2": "vassāni → vassānaṃ (bj, sya-all, mr ^snp5.7#671 [Upasīvamāṇavapucchā])",
  "cnd10:38.2": "bahūni vassāni → bahunnaṃ vassānaṃ (sya-all)",
  "cnd10:39.2": "na bhaveyyāti → na bhaveyya (bj, sya-all)",
  "cnd10:41.1": "Acci → accī (^snp5.7#672 [Upasīvamāṇavapucchā])",
  "cnd10:42.1": "khittā → khittaṃ (sya-all)",
  "cnd10:42.2": "parittā vātā adhimattā vātā → vātā kāḷavātā (bj, mr)",
  "cnd10:43.3": "saṅkhaṃ → amukaṃ nāma disaṃ gatoti saṅkhaṃ (sya-all)",
  "cnd10:44.7": "Tadaṅgaṃ samatikkamā → tadaṅgasamatikkamā (bj) | tadaṅgasamatikkama (sya-all) | tadaṅgaṃ samatikkamma (mr)",
  "cnd10:53.2": "vajjuṃ → vajju (bj, sya-all, pts-vp-pli1ed)",
  "cnd10:53.3": "samūhatesu → samohatesu (^snp5.7#674 [Upasīvamāṇavapucchā])",
  "cnd10:55.1": "yena taṃ rāgena → yena rāgena (bj, sya-all, mr)",
  "cnd10:55.2": "aniṭṭhaṅgatoti → aniṭṭhāgatoti (mr)",
  "cnd10:56.1": "sabbāsu dhātūsu → sabbesu dhātūsu (bj)"
}