{
  "cnd7:6.4": [
    "anabhāvaṃkatā → anābhāvakatā (bj) | anabhāvaṅgatā (s1-3)"
  ],
  "cnd7:15.1": [
    "pañhena atthiko āgatomhi → pañhatthikāmhā āgatā (s1-3)"
  ],
  "cnd7:15.6": [
    "bhāranti → vissajjetu ... (bj) | visajjetuṃ sandassetuṃ bhaṇitunti (s1-3)"
  ],
  "cnd7:17.4": [
    "aviruddhakasāvakānaṃ aviruddhakā → avaruddhakasāvakānaṃ avaruddhakā (bj, s1-3)"
  ],
  "cnd7:18.1": [
    "mālāgandhavilepanaṃ → mālāgandhaṃ vilepanaṃ (s1-3)"
  ],
  "cnd7:18.9": [
    "yaññayājakā → yaññayajakā (s1-3)"
  ],
  "cnd7:18.11": [
    "Bahukānaṃ → bahukā (bj)"
  ],
  "cnd7:20.2": [
    "kapaṇaddhikavanibbakayācakā → ... vaṇibbakayāvakā (bj) | yācakavaṇibbakasāvakā (s1-3)"
  ],
  "cnd7:21.5": [
    "tīraṇāya vibhūtatthāya vibhāvanatthāya → tīraṇāya vibhāvanāya (bj) | tiraṇāya vibhāvanatthāya vibhūtatthāya (s1-3)"
  ],
  "cnd7:23.2": [
    "saṃsayapakkhando → saṃsayaṃ pakkhanno (s1-3)"
  ],
  "cnd7:26.3": [
    "visajjeti → vissajjeti (bj, mr)"
  ],
  "cnd7:30.4": [
    "Āsīsamānā → asiṃsamānā (bj) | āsiṃsamānā (s1-3, pts1)",
    "itthattaṃ → itthabhāvaṃ (bj, mr) | itthataṃ (s1-3)"
  ],
  "cnd7:31.2": [
    "pariyādiyanavacanametaṃ → pariyādāyavacanametaṃ (s1-3)"
  ],
  "cnd7:34.2": [
    "cātumahārājikesu → cātummahārājikesu (bj, s1-3, pts1)"
  ],
  "cnd7:38.3": [
    "Yaññamakappayiṃsu → yaññamakappiṃsu (s1-3)"
  ],
  "cnd7:38.4": [
    "Kaccisu → kaccissu (s1-3 ^snp5.4#1139 [Puṇṇakamāṇavapucchā])"
  ],
  "cnd7:38.5": [
    "Atāruṃ → atāru (bj, c1)"
  ],
  "cnd7:40.1": [
    "yaññapathe → yepi yaññapathe (bj)"
  ],
  "cnd7:40.12": [
    "tappoṇā → tapponā (bj)"
  ],
  "cnd7:41.1": [
    "jarāmaraṇaṃ → jātijarāmaraṇaṃ (bj, s1-3)"
  ],
  "cnd7:44.1": [
    "Āsīsanti → āsiṃsanti (bj, s1-3)"
  ],
  "cnd7:46.1": [
    "dakkhiṇeyye → dakkhiṇeyyaṃ (s1-3)"
  ],
  "cnd7:46.3": [
    "dinnaṃ → piyaṃ dinnaṃ (s1-3)"
  ],
  "cnd7:51.3": [
    "gadhitā → gathitā (bj)",
    "ajjhosannā → ajjhopannā (bj, s1-3)"
  ],
  "cnd7:58.1": [
    "vītivattayi → vītivatti (mr)"
  ],
  "cnd7:61.1": [
    "lokasmi → lokasmiṃ (bj, s1-3, mr)",
    "paroparāni → parovarāni (bj)"
  ],
  "cnd7:62.4": [
    "paraṃ → oparaṃ (?)"
  ],
  "cnd7:62.6": [
    "Oraṃ → opāraṃ (s1-3)"
  ],
  "cnd7:64.8": [
    "vijjhātattā → nijjhātattā (mr)"
  ],
  "cnd7:64.9": [
    "byantīkataṃ → byantikataṃ (mr)"
  ],
  "cnd7:65.2": [
    "bhasmani → gammani (s1-3)"
  ],
  "cnd7:65.3": [
    "hadayaṃ → tapparassa (s1-3)"
  ],
  "cnd7:66.3": [
    "byāpatti → vyāpatti (bj)",
    "asuropo → assuropo (s1-3)"
  ],
  "cnd7:67.2": [
    "kañci → kiñci (mr)"
  ],
  "cnd7:67.4": [
    "pharusavācaṃ nicchāraṇo → pharusavācaṃ nicchārano (bj) | pharusavācanicchāraṇo (s1-3)"
  ],
  "cnd7:67.12": [
    "jīvitāvoropano → jīvitapanāsano (s1-3)"
  ]
}