{
  "pv19:4.1": "sc1,  vns227,  pts2ed27",
  "pv19:5.1": "sc2,  vns228",
  "pv19:6.1": "sc3,  vns229",
  "pv19:7.1": "sc4,  vns230",
  "pv19:8.1": "sc5,  vns231",
  "pv19:9.1": "sc6,  vns232",
  "pv19:10.1": "sc7,  vns233",
  "pv19:11.1": "sc8,  vns234,  pts2ed28",
  "pv19:12.1": "sc9,  vns235",
  "pv19:13.1": "sc10,  vns236",
  "pv19:14.1": "sc11,  vns237",
  "pv19:15.1": "sc12,  vns238",
  "pv19:16.1": "sc13,  vns239",
  "pv19:17.1": "sc14,  vns240",
  "pv19:18.1": "sc15,  vns241",
  "pv19:19.1": "sc16,  vns242",
  "pv19:20.1": "sc17,  vns243",
  "pv19:21.1": "sc18,  vns244",
  "pv19:22.1": "sc19,  vns245",
  "pv19:23.1": "sc20"
}