{
  "pli-tv-bi-vb-pc11:6.1": "sc1, pts-cs11.1, pts-vp-en3.263, ms2V_2671",
  "pli-tv-bi-vb-pc11:7.1": "sc2, ms2V_2672",
  "pli-tv-bi-vb-pc11:8.1": "sc3, ms2V_2673",
  "pli-tv-bi-vb-pc11:9.1": "sc4, pts-cs11.2.1, ms2V_2674",
  "pli-tv-bi-vb-pc11:10.1": "sc5, ms2V_2675",
  "pli-tv-bi-vb-pc11:11.1": "sc6, pts-vp-pli4.269, pts-vp-pli4.269, pts-vp-en3.264, ms2V_2676",
  "pli-tv-bi-vb-pc11:12.1": "sc7, ms2V_2677",
  "pli-tv-bi-vb-pc11:13.1": "sc8, ms2V_2678",
  "pli-tv-bi-vb-pc11:14.1": "sc9, ms2V_2679",
  "pli-tv-bi-vb-pc11:15.1": "sc10, ms2V_2680",
  "pli-tv-bi-vb-pc11:16.1": "sc11, pts-cs11.2.2, ms2V_2681",
  "pli-tv-bi-vb-pc11:17.1": "sc12, ms2V_2682"
}