{
  "mil6.3.2:1.1": "ms28Mi_1244, msdiv191, sc1",
  "mil6.3.2:2.1": "ms28Mi_1245, pts-vp-pli285, sc2",
  "mil6.3.2:3.1": "ms28Mi_1246, sc3",
  "mil6.3.2:4.1": "ms28Mi_1247, sc4",
  "mil6.3.2:5.1": "ms28Mi_1248, sc5",
  "mil6.3.2:6.1": "ms28Mi_1249, sc6",
  "mil6.3.2:7.1": "ms28Mi_1250, pts-vp-pli286, sc7",
  "mil6.3.2:8.1": "ms28Mi_1251, sc8",
  "mil6.3.2:9.1": "ms28Mi_1252, sc9",
  "mil6.3.2:10.1": "ms28Mi_1253, sc10",
  "mil6.3.2:11.1": "ms28Mi_1254, pts-vp-pli287, sc11",
  "mil6.3.2:12.1": "ms28Mi_1255, sc12",
  "mil6.3.2:13.1": "ms28Mi_1256, pts-vp-pli288, sc13",
  "mil6.3.2:14.1": "ms28Mi_1257, sc14",
  "mil6.3.2:15.1": "ms28Mi_1258, sc15",
  "mil6.3.2:16.1": "ms28Mi_1259, pts-vp-pli289, sc16",
  "mil6.3.2:17.1": "ms28Mi_1260, sc17",
  "mil6.3.2:18.1": "ms28Mi_1261, pts-vp-pli290, sc18",
  "mil6.3.2:19.1": "ms28Mi_1262, sc19"
}