{
  "patthana13.3:1.1": "ms40P13_33, msdiv17, sc1",
  "patthana13.3:2.1": "ms40P13_34, msdiv18, sc2",
  "patthana13.3:3.1": "ms40P13_35, msdiv19, sc3",
  "patthana13.3:4.1": "ms40P13_36, msdiv20, sc4",
  "patthana13.3:5.1": "ms40P13_37, sc5",
  "patthana13.3:6.1": "ms40P13_38, msdiv21, sc6",
  "patthana13.3:7.1": "ms40P13_39, sc7",
  "patthana13.3:8.1": "ms40P13_40, sc8",
  "patthana13.3:9.1": "ms40P13_41, sc9",
  "patthana13.3:10.1": "ms40P13_42, msdiv22, sc10",
  "patthana13.3:11.1": "ms40P13_43, sc11",
  "patthana13.3:12.1": "ms40P13_44, sc12",
  "patthana13.3:13.1": "ms40P13_45, msdiv23, sc13",
  "patthana13.3:14.1": "ms40P13_46, msdiv24, sc14",
  "patthana13.3:15.1": "ms40P13_47, sc15",
  "patthana13.3:16.1": "ms40P13_48, sc16",
  "patthana13.3:17.1": "ms40P13_49, msdiv25, sc17"
}