{
  "tha-ap543:4.1": "sc1,  pts2.489",
  "tha-ap543:5.1": "sc2",
  "tha-ap543:6.1": "sc3",
  "tha-ap543:7.1": "sc4",
  "tha-ap543:8.1": "sc5",
  "tha-ap543:9.1": "sc6",
  "tha-ap543:10.1": "sc7",
  "tha-ap543:11.1": "sc8",
  "tha-ap543:12.1": "sc9",
  "tha-ap543:13.1": "sc10",
  "tha-ap543:14.1": "sc11",
  "tha-ap543:15.1": "sc12",
  "tha-ap543:16.1": "sc13",
  "tha-ap543:17.1": "sc14",
  "tha-ap543:18.1": "sc15,  pts2.490",
  "tha-ap543:19.1": "sc16",
  "tha-ap543:20.1": "sc17",
  "tha-ap543:21.1": "sc18",
  "tha-ap543:22.1": "sc19",
  "tha-ap543:23.1": "sc20",
  "tha-ap543:24.1": "sc21",
  "tha-ap543:25.1": "sc22",
  "tha-ap543:26.1": "sc23",
  "tha-ap543:27.1": "sc24",
  "tha-ap543:28.1": "sc25",
  "tha-ap543:29.1": "sc26",
  "tha-ap543:30.1": "sc27",
  "tha-ap543:31.1": "sc28",
  "tha-ap543:32.1": "sc29",
  "tha-ap543:33.1": "sc30,  pts2.491",
  "tha-ap543:34.1": "sc31",
  "tha-ap543:35.1": "sc32",
  "tha-ap543:36.1": "sc33",
  "tha-ap543:37.1": "sc34",
  "tha-ap543:38.1": "sc35"
}